<?xml version="1.0" encoding="UTF-8"?><record_update sys_domain="global" table="sys_cb_topic">
    <sys_cb_topic action="DELETE">
        <applicability/>
        <applicability_mode>query</applicability_mode>
        <autopilot_topic>false</autopilot_topic>
        <category>6d51816bdbc50110cd98f1be3b961989</category>
        <channels/>
        <connect_queue/>
        <description>This is out of the BOX.</description>
        <expose_on_palette>false</expose_on_palette>
        <flexible_conversation_switching>true</flexible_conversation_switching>
        <graph>{"graph_api_version":"1.0.36","variables":{},"goals":{"primary":{"id":"primary","trigger":{"type":"primary"},"name":"primary","applicability":"","description":"","nodes":{"93727cbdc0e1455ea5c8caf381a2db62":{"id":"93727cbdc0e1455ea5c8caf381a2db62","stepType":"Start","name":"Start","greetingResponse":{"mode":"simple","value":""}},"3db0ff9d15f74a1891093f88e9c301a1":{"id":"3db0ff9d15f74a1891093f88e9c301a1","stepType":"TerminateGoal","name":"End","confirmationMessage":{"mode":"simple","value":""}}},"edges":[{"id":"7b33da3adde8469e8a89e0d5f180eec2","edgeType":"Edge","source":"93727cbdc0e1455ea5c8caf381a2db62","target":"3db0ff9d15f74a1891093f88e9c301a1","sourcePort":"","targetPort":""}]}}}</graph>
        <key_phrases>Create incident from Chat,incident,problem,issue,trouble</key_phrases>
        <library>false</library>
        <live_agent>false</live_agent>
        <name>Create incident from Chat</name>
        <nlu_intent/>
        <nlu_intent_label/>
        <nlu_model/>
        <nlu_model_label/>
        <nlu_provider/>
        <palette_label/>
        <roles/>
        <source_topic_id/>
        <sys_class_name>sys_cb_topic</sys_class_name>
        <sys_created_by>admin</sys_created_by>
        <sys_created_on>2022-01-20 16:15:00</sys_created_on>
        <sys_domain>global</sys_domain>
        <sys_id>3a595d23db490110cd98f1be3b9619e3</sys_id>
        <sys_mod_count>0</sys_mod_count>
        <sys_name>Create incident from Chat</sys_name>
        <sys_package display_value="CI NLU - Krishna " source="8b09b863dbc50110cd98f1be3b96198c">8b09b863dbc50110cd98f1be3b96198c</sys_package>
        <sys_policy/>
        <sys_scope display_value="CI NLU - Krishna ">8b09b863dbc50110cd98f1be3b96198c</sys_scope>
        <sys_update_name>sys_cb_topic_3a595d23db490110cd98f1be3b9619e3</sys_update_name>
        <sys_updated_by>admin</sys_updated_by>
        <sys_updated_on>2022-01-20 16:15:00</sys_updated_on>
        <triggerable_by_notification>false</triggerable_by_notification>
        <type>STANDARD</type>
        <variables/>
    </sys_cb_topic>
    <sys_variable_value action="DELETE" query="document_key=3a595d23db490110cd98f1be3b9619e3"/>
    <sys_update_version action="INSERT_OR_UPDATE">
        <action>DELETE</action>
        <application display_value="CI NLU - Krishna ">8b09b863dbc50110cd98f1be3b96198c</application>
        <file_path/>
        <instance_id>3d1fa96cdb4ef60089535d00cf961994</instance_id>
        <instance_name>dev34182</instance_name>
        <name>sys_cb_topic_3a595d23db490110cd98f1be3b9619e3</name>
        <payload><![CDATA[<?xml version="1.0" encoding="UTF-8"?><record_update sys_domain="global" table="sys_cb_topic"><sys_cb_topic action="INSERT_OR_UPDATE"><applicability/><applicability_mode>query</applicability_mode><autopilot_topic>false</autopilot_topic><category>6d51816bdbc50110cd98f1be3b961989</category><channels/><connect_queue/><description>This is out of the BOX.</description><expose_on_palette>false</expose_on_palette><flexible_conversation_switching>true</flexible_conversation_switching><graph>{"graph_api_version":"1.0.36","variables":{},"goals":{"primary":{"id":"primary","trigger":{"type":"primary"},"name":"primary","applicability":"","description":"","nodes":{"93727cbdc0e1455ea5c8caf381a2db62":{"id":"93727cbdc0e1455ea5c8caf381a2db62","stepType":"Start","name":"Start","greetingResponse":{"mode":"simple","value":""}},"3db0ff9d15f74a1891093f88e9c301a1":{"id":"3db0ff9d15f74a1891093f88e9c301a1","stepType":"TerminateGoal","name":"End","confirmationMessage":{"mode":"simple","value":""}}},"edges":[{"id":"7b33da3adde8469e8a89e0d5f180eec2","edgeType":"Edge","source":"93727cbdc0e1455ea5c8caf381a2db62","target":"3db0ff9d15f74a1891093f88e9c301a1","sourcePort":"","targetPort":""}]}}}</graph><key_phrases>Create incident from Chat,incident,problem,issue,trouble</key_phrases><library>false</library><live_agent>false</live_agent><name>Create incident from Chat</name><nlu_intent/><nlu_intent_label/><nlu_model/><nlu_model_label/><nlu_provider/><palette_label/><roles/><source_topic_id/><sys_class_name>sys_cb_topic</sys_class_name><sys_created_by>admin</sys_created_by><sys_created_on>2022-01-20 16:15:00</sys_created_on><sys_domain>global</sys_domain><sys_id>3a595d23db490110cd98f1be3b9619e3</sys_id><sys_mod_count>0</sys_mod_count><sys_name>Create incident from Chat</sys_name><sys_package display_value="CI NLU - Krishna " source="8b09b863dbc50110cd98f1be3b96198c">8b09b863dbc50110cd98f1be3b96198c</sys_package><sys_policy/><sys_scope display_value="CI NLU - Krishna ">8b09b863dbc50110cd98f1be3b96198c</sys_scope><sys_update_name>sys_cb_topic_3a595d23db490110cd98f1be3b9619e3</sys_update_name><sys_updated_by>admin</sys_updated_by><sys_updated_on>2022-01-20 16:15:00</sys_updated_on><triggerable_by_notification>false</triggerable_by_notification><type>STANDARD</type><variables/></sys_cb_topic><sys_variable_value action="delete_multiple" query="document_key=3a595d23db490110cd98f1be3b9619e3"/></record_update>]]></payload>
        <payload_hash>-1347165629</payload_hash>
        <record_name>Create incident from Chat</record_name>
        <reverted_from/>
        <source>a9a53e098d272010d152b9319a2024ca</source>
        <source_table>sys_update_set</source_table>
        <state>previous</state>
        <sys_created_by>admin</sys_created_by>
        <sys_created_on>2022-01-20 16:15:00</sys_created_on>
        <sys_id>8b5955e3db490110cd98f1be3b9619a0</sys_id>
        <sys_mod_count>0</sys_mod_count>
        <sys_recorded_at>17e784517090000001</sys_recorded_at>
        <sys_updated_by>admin</sys_updated_by>
        <sys_updated_on>2022-01-20 16:15:00</sys_updated_on>
        <type>Topic</type>
        <update_guid>c35955e339490110932accb6a56817a0</update_guid>
        <update_guid_history>c35955e339490110932accb6a56817a0:-1347165629</update_guid_history>
    </sys_update_version>
    <sys_metadata_delete action="INSERT_OR_UPDATE">
        <sys_audit_delete/>
        <sys_class_name>sys_metadata_delete</sys_class_name>
        <sys_created_by>admin</sys_created_by>
        <sys_created_on>2022-01-20 17:03:33</sys_created_on>
        <sys_db_object display_value="" name="sys_cb_topic">sys_cb_topic</sys_db_object>
        <sys_id>c08330e4c6b048dba143529e3bc90819</sys_id>
        <sys_metadata>3a595d23db490110cd98f1be3b9619e3</sys_metadata>
        <sys_mod_count>0</sys_mod_count>
        <sys_name>Create incident from Chat</sys_name>
        <sys_package display_value="CI NLU - Krishna " source="8b09b863dbc50110cd98f1be3b96198c">8b09b863dbc50110cd98f1be3b96198c</sys_package>
        <sys_parent/>
        <sys_policy/>
        <sys_scope display_value="CI NLU - Krishna ">8b09b863dbc50110cd98f1be3b96198c</sys_scope>
        <sys_scope_delete display_value="">427756f0f0cf4a8fba37a612ed1cff49</sys_scope_delete>
        <sys_update_name>sys_cb_topic_3a595d23db490110cd98f1be3b9619e3</sys_update_name>
        <sys_update_version display_value="sys_cb_topic_3a595d23db490110cd98f1be3b9619e3">8b5955e3db490110cd98f1be3b9619a0</sys_update_version>
        <sys_updated_by>admin</sys_updated_by>
        <sys_updated_on>2022-01-20 17:03:33</sys_updated_on>
    </sys_metadata_delete>
</record_update>
